[{"player": {"name": "Mateo Kova\u010di\u0107", "slug": "mateo-kovacic", "shortName": "M. Kova\u010di\u0107", "position": "M", "jerseyNumber": "8", "userCount": 26243, "id": 136710, "fieldTranslations": {"nameTranslation": {"ar": "\u0643\u0648\u0641\u0627\u0633\u064a\u062a\u0634, \u0645\u0627\u062a\u064a\u0648"}, "shortNameTranslation": {"ar": "\u0645. \u0643\u0648\u0641\u0627\u0633\u064a\u062a\u0634"}}}, "isHome": true, "shotType": "save", "situation": "assisted", "playerCoordinates": {"x": 14.4, "y": 39.7, "z": 0}, "bodyPart": "left-foot", "goalMouthLocation": "high-centre", "goalMouthCoordinates": {"x": 0, "y": 48.8, "z": 20.3}, "blockCoordinates": {"x": 2.9, "y": 47.1, "z": 0}, "xg": 0.093903802335262, "xgot": 0.0628, "id": 3378994, "time": 90, "addedTime": 8, "timeSeconds": 5878, "draw": {"start": {"x": 39.7, "y": 14.4}, "block": {"x": 47.1, "y": 2.9}, "end": {"x": 51.2, "y": 0}, "goal": {"x": 51.2, "y": 79.7}}, "reversedPeriodTime": 1, "reversedPeriodTimeSeconds": 422, "incidentType": "shot"}, {"player": {"name": "Klaus Gjasula", "slug": "klaus-gjasula", "shortName": "K. Gjasula", "position": "D", "jerseyNumber": "23", "userCount": 320, "id": 163673, "fieldTranslations": {"nameTranslation": {"ar": "\u062c\u0627\u0633\u0648\u0644\u0627, \u0643\u0644\u0627\u0648\u0633"}, "shortNameTranslation": {"ar": "\u0643. \u062c\u0627\u0633\u0648\u0644\u0627"}}}, "isHome": false, "shotType": "block", "situation": "assisted", "playerCoordinates": {"x": 19.8, "y": 49.3, "z": 0}, "bodyPart": "right-foot", "goalMouthLocation": "low-left", "goalMouthCoordinates": {"x": 0, "y": 52.9, "z": 19}, "blockCoordinates": {"x": 11.6, "y": 48.4, "z": 0}, "xg": 0.077796921133995, "id": 3379019, "time": 90, "addedTime": 7, "timeSeconds": 5794, "draw": {"start": {"x": 49.3, "y": 19.8}, "block": {"x": 48.4, "y": 11.6}, "end": {"x": 47.1, "y": 0}, "goal": {"x": 47.1, "y": 81}}, "reversedPeriodTime": 1, "reversedPeriodTimeSeconds": 506, "incidentType": "shot"}, {"player": {"name": "Klaus Gjasula", "slug": "klaus-gjasula", "shortName": "K. Gjasula", "position": "D", "jerseyNumber": "23", "userCount": 320, "id": 163673, "fieldTranslations": {"nameTranslation": {"ar": "\u062c\u0627\u0633\u0648\u0644\u0627, \u0643\u0644\u0627\u0648\u0633"}, "shortNameTranslation": {"ar": "\u0643. \u062c\u0627\u0633\u0648\u0644\u0627"}}}, "isHome": false, "shotType": "goal", "goalType": "regular", "situation": "regular", "playerCoordinates": {"x": 11.5, "y": 50, "z": 0}, "bodyPart": "left-foot", "goalMouthLocation": "low-left", "goalMouthCoordinates": {"x": 0, "y": 52.9, "z": 4.4}, "xg": 0.21742527186871, "xgot": 0.6508, "id": 3378993, "time": 90, "addedTime": 5, "timeSeconds": 5663, "draw": {"start": {"x": 50, "y": 11.5}, "end": {"x": 47.1, "y": 0}, "goal": {"x": 47.1, "y": 95.6}}, "reversedPeriodTime": 1, "reversedPeriodTimeSeconds": 637, "incidentType": "shot"}, {"player": {"name": "Mirlind Daku", "firstName": "", "lastName": "", "slug": "mirlind-daku", "shortName": "M. Daku", "position": "F", "jerseyNumber": "44", "userCount": 655, "id": 970516}, "isHome": false, "shotType": "block", "situation": "assisted", "playerCoordinates": {"x": 9.5, "y": 45.8, "z": 0}, "bodyPart": "right-foot", "goalMouthLocation": "low-centre", "goalMouthCoordinates": {"x": 0, "y": 48.6, "z": 19}, "blockCoordinates": {"x": 6, "y": 47.8, "z": 0}, "xg": 0.1141047924757, "id": 3378992, "time": 90, "addedTime": 3, "timeSeconds": 5549, "draw": {"start": {"x": 45.8, "y": 9.5}, "block": {"x": 47.8, "y": 6}, "end": {"x": 51.4, "y": 0}, "goal": {"x": 51.4, "y": 81}}, "reversedPeriodTime": 1, "reversedPeriodTimeSeconds": 751, "incidentType": "shot"}, {"player": {"name": "Arber Hoxha", "slug": "arber-hoxha", "shortName": "A. Hoxha", "position": "M", "jerseyNumber": "20", "userCount": 602, "id": 890663}, "isHome": false, "shotType": "save", "situation": "assisted", "playerCoordinates": {"x": 21.8, "y": 56, "z": 0}, "bodyPart": "right-foot", "goalMouthLocation": "low-left", "goalMouthCoordinates": {"x": 0, "y": 52, "z": 3.2}, "blockCoordinates": {"x": 2.8, "y": 51.8, "z": 0}, "xg": 0.065928988158703, "xgot": 0.1063, "id": 3378991, "time": 90, "timeSeconds": 5344, "draw": {"start": {"x": 56, "y": 21.8}, "block": {"x": 51.8, "y": 2.8}, "end": {"x": 48, "y": 0}, "goal": {"x": 48, "y": 96.8}}, "reversedPeriodTime": 1, "reversedPeriodTimeSeconds": 56, "incidentType": "shot"}, {"player": {"name": "Martin Baturina", "firstName": "", "lastName": "", "slug": "martin-baturina", "shortName": "M. Baturina", "position": "M", "jerseyNumber": "10", "userCount": 3507, "id": 1090019, "fieldTranslations": {"nameTranslation": {"ar": "\u0645\u0627\u0631\u062a\u0646 \u0628\u0627\u062a\u0648\u0631\u064a\u0646\u0627"}, "shortNameTranslation": {"ar": "\u0645. \u0628\u0627\u062a\u0648\u0631\u064a\u0646\u0627"}}}, "isHome": true, "shotType": "save", "situation": "fast-break", "playerCoordinates": {"x": 7.2, "y": 30.2, "z": 0}, "bodyPart": "right-foot", "goalMouthLocation": "low-right", "goalMouthCoordinates": {"x": 0, "y": 46.8, "z": 8.9}, "blockCoordinates": {"x": 1.4, "y": 44.4, "z": 0}, "xg": 0.07366743683815, "xgot": 0.5016, "id": 3378990, "time": 89, "timeSeconds": 5300, "draw": {"start": {"x": 30.2, "y": 7.2}, "block": {"x": 44.4, "y": 1.4}, "end": {"x": 53.2, "y": 0}, "goal": {"x": 53.2, "y": 91.1}}, "reversedPeriodTime": 2, "reversedPeriodTimeSeconds": 100, "incidentType": "shot"}, {"player": {"name": "Luka Modri\u0107", "slug": "luka-modric", "shortName": "L. Modri\u0107", "position": "M", "jerseyNumber": "10", "userCount": 185171, "id": 15466, "fieldTranslations": {"nameTranslation": {"ar": "\u0645\u0648\u062f\u0631\u064a\u062a\u0634, \u0644\u0648\u0643\u0627"}, "shortNameTranslation": {"ar": "\u0644. \u0645\u0648\u062f\u0631\u064a\u062a\u0634"}}}, "isHome": true, "shotType": "miss", "situation": "assisted", "playerCoordinates": {"x": 23.5, "y": 60.1, "z": 0}, "bodyPart": "right-foot", "goalMouthLocation": "close-left", "goalMouthCoordinates": {"x": 0, "y": 57.8, "z": 15.3}, "xg": 0.049103196710348, "id": 3378974, "time": 88, "timeSeconds": 5258, "draw": {"start": {"x": 60.1, "y": 23.5}, "end": {"x": 42.2, "y": 0}, "goal": {"x": 42.2, "y": 84.7}}, "reversedPeriodTime": 3, "reversedPeriodTimeSeconds": 142, "incidentType": "shot"}, {"player": {"name": "Ante Budimir", "firstName": "", "lastName": "", "slug": "ante-budimir", "shortName": "A. Budimir", "position": "F", "jerseyNumber": "17", "userCount": 3969, "id": 37318, "fieldTranslations": {"nameTranslation": {"ar": "\u0628\u0648\u062f\u064a\u0645\u064a\u0631, \u0623\u0646\u062a\u064a"}, "shortNameTranslation": {"ar": "\u0623. \u0628\u0648\u062f\u064a\u0645\u064a\u0631"}}}, "isHome": true, "shotType": "save", "situation": "set-piece", "playerCoordinates": {"x": 12.5, "y": 46, "z": 0}, "bodyPart": "left-foot", "goalMouthLocation": "low-left", "goalMouthCoordinates": {"x": 0, "y": 53.8, "z": 1.9}, "blockCoordinates": {"x": 2.9, "y": 49.8, "z": 0}, "xg": 0.069601655006409, "xgot": 0.3436, "id": 3378973, "time": 80, "timeSeconds": 4751, "draw": {"start": {"x": 46, "y": 12.5}, "block": {"x": 49.8, "y": 2.9}, "end": {"x": 46.2, "y": 0}, "goal": {"x": 46.2, "y": 98.1}}, "reversedPeriodTime": 11, "reversedPeriodTimeSeconds": 649, "incidentType": "shot"}, {"player": {"name": "Klaus Gjasula", "slug": "klaus-gjasula", "shortName": "K. Gjasula", "position": "D", "jerseyNumber": "23", "userCount": 320, "id": 163673, "fieldTranslations": {"nameTranslation": {"ar": "\u062c\u0627\u0633\u0648\u0644\u0627, \u0643\u0644\u0627\u0648\u0633"}, "shortNameTranslation": {"ar": "\u0643. \u062c\u0627\u0633\u0648\u0644\u0627"}}}, "isHome": true, "shotType": "goal", "goalType": "own", "situation": "regular", "playerCoordinates": {"x": 7.4, "y": 47.6, "z": 0}, "bodyPart": "right-foot", "goalMouthLocation": "high-left", "goalMouthCoordinates": {"x": 0, "y": 53.6, "z": 20.3}, "id": 3378945, "time": 76, "timeSeconds": 4545, "draw": {"start": {"x": 47.6, "y": 7.4}, "end": {"x": 46.4, "y": 0}, "goal": {"x": 46.4, "y": 79.7}}, "reversedPeriodTime": 15, "reversedPeriodTimeSeconds": 855, "incidentType": "shot"}, {"player": {"name": "Luka Su\u010di\u0107", "firstName": "", "lastName": "", "slug": "luka-sucic", "shortName": "L. Su\u010di\u0107", "position": "M", "jerseyNumber": "10", "userCount": 4131, "id": 949156, "fieldTranslations": {"nameTranslation": {"ar": "\u0644\u0648\u0643\u0627 \u0633\u0648\u062a\u0634\u064a\u062a\u0634"}, "shortNameTranslation": {"ar": "\u0644. \u0633\u0648\u062a\u0634\u064a\u062a\u0634"}}}, "isHome": true, "shotType": "save", "situation": "assisted", "playerCoordinates": {"x": 8.3, "y": 49.1, "z": 0}, "bodyPart": "left-foot", "goalMouthLocation": "low-centre", "goalMouthCoordinates": {"x": 0, "y": 50.9, "z": 19}, "blockCoordinates": {"x": 5.3, "y": 49.1, "z": 0}, "xg": 0.51945060491562, "id": 3378944, "time": 76, "timeSeconds": 4544, "draw": {"start": {"x": 49.1, "y": 8.3}, "block": {"x": 49.1, "y": 5.3}, "end": {"x": 49.1, "y": 0}, "goal": {"x": 49.1, "y": 81}}, "reversedPeriodTime": 15, "reversedPeriodTimeSeconds": 856, "incidentType": "shot"}, {"player": {"name": "Ante Budimir", "firstName": "", "lastName": "", "slug": "ante-budimir", "shortName": "A. Budimir", "position": "F", "jerseyNumber": "17", "userCount": 3969, "id": 37318, "fieldTranslations": {"nameTranslation": {"ar": "\u0628\u0648\u062f\u064a\u0645\u064a\u0631, \u0623\u0646\u062a\u064a"}, "shortNameTranslation": {"ar": "\u0623. \u0628\u0648\u062f\u064a\u0645\u064a\u0631"}}}, "isHome": true, "shotType": "save", "situation": "regular", "playerCoordinates": {"x": 4.4, "y": 56.2, "z": 0}, "bodyPart": "left-foot", "goalMouthLocation": "low-centre", "goalMouthCoordinates": {"x": 0, "y": 48.9, "z": 1.3}, "blockCoordinates": {"x": 3.6, "y": 55.1, "z": 0}, "xg": 0.14565892517567, "xgot": 0.6796, "id": 3379020, "time": 75, "timeSeconds": 4490, "draw": {"start": {"x": 56.2, "y": 4.4}, "block": {"x": 55.1, "y": 3.6}, "end": {"x": 51.1, "y": 0}, "goal": {"x": 51.1, "y": 98.7}}, "reversedPeriodTime": 16, "reversedPeriodTimeSeconds": 910, "incidentType": "shot"}, {"player": {"name": "Andrej Kramari\u0107", "slug": "andrej-kramaric", "shortName": "A. Kramari\u0107", "position": "F", "jerseyNumber": "27", "userCount": 7358, "id": 67647, "fieldTranslations": {"nameTranslation": {"ar": "\u0643\u0631\u0627\u0645\u0627\u0631\u064a\u0643, \u0623\u0646\u062f\u0631\u064a"}, "shortNameTranslation": {"ar": "\u0623. \u0643\u0631\u0627\u0645\u0627\u0631\u064a\u0643"}}}, "isHome": true, "shotType": "goal", "goalType": "regular", "situation": "assisted", "playerCoordinates": {"x": 10.6, "y": 44.8, "z": 0}, "bodyPart": "right-foot", "goalMouthLocation": "low-left", "goalMouthCoordinates": {"x": 0, "y": 53, "z": 3.2}, "xg": 0.2172809690237, "xgot": 0.7061, "id": 3378943, "time": 74, "timeSeconds": 4398, "draw": {"start": {"x": 44.8, "y": 10.6}, "end": {"x": 47, "y": 0}, "goal": {"x": 47, "y": 96.8}}, "reversedPeriodTime": 17, "reversedPeriodTimeSeconds": 1002, "incidentType": "shot"}, {"player": {"name": "Taulant Seferi", "slug": "taulant-seferi", "shortName": "T. Seferi", "position": "M", "jerseyNumber": "99", "userCount": 429, "id": 279487, "fieldTranslations": {"nameTranslation": {"ar": "\u062a\u0627\u0648\u0644\u0627\u0646\u062a \u0633\u064a\u0641\u064a\u0631\u064a"}, "shortNameTranslation": {"ar": "\u062a. \u0633\u064a\u0641\u064a\u0631\u064a"}}}, "isHome": false, "shotType": "save", "situation": "regular", "playerCoordinates": {"x": 26, "y": 40.7, "z": 0}, "bodyPart": "right-foot", "goalMouthLocation": "low-left", "goalMouthCoordinates": {"x": 0, "y": 51.9, "z": 2.5}, "blockCoordinates": {"x": 2.5, "y": 50, "z": 0}, "xg": 0.016290040686727, "xgot": 0.084, "id": 3378942, "time": 73, "timeSeconds": 4374, "draw": {"start": {"x": 40.7, "y": 26}, "block": {"x": 50, "y": 2.5}, "end": {"x": 48.1, "y": 0}, "goal": {"x": 48.1, "y": 97.5}}, "reversedPeriodTime": 18, "reversedPeriodTimeSeconds": 1026, "incidentType": "shot"}, {"player": {"name": "Mario Pa\u0161ali\u0107", "slug": "mario-pasalic", "shortName": "M. Pa\u0161ali\u0107", "position": "M", "jerseyNumber": "8", "userCount": 6916, "id": 190437, "fieldTranslations": {"nameTranslation": {"ar": "\u0628\u0627\u0632\u0627\u0644\u064a\u062a\u0634, \u0645\u0627\u0631\u064a\u0648"}, "shortNameTranslation": {"ar": "\u0645. \u0628\u0627\u0632\u0627\u0644\u064a\u062a\u0634"}}}, "isHome": true, "shotType": "miss", "situation": "assisted", "playerCoordinates": {"x": 6, "y": 53.2, "z": 0}, "bodyPart": "head", "goalMouthLocation": "high-right", "goalMouthCoordinates": {"x": 0, "y": 42.9, "z": 75}, "xg": 0.17674289643764, "id": 3378914, "time": 69, "timeSeconds": 4089, "draw": {"start": {"x": 53.2, "y": 6}, "end": {"x": 57.1, "y": 0}, "goal": {"x": 57.1, "y": 25}}, "reversedPeriodTime": 22, "reversedPeriodTimeSeconds": 1311, "incidentType": "shot"}, {"player": {"name": "Nedim Bajrami", "firstName": "", "lastName": "", "slug": "nedim-bajrami", "shortName": "N. Bajrami", "position": "M", "jerseyNumber": "11", "userCount": 1625, "id": 825861, "fieldTranslations": {"nameTranslation": {"ar": "\u0646\u062f\u064a\u0645 \u0628\u0627\u064a\u0631\u0627\u0645\u064a"}, "shortNameTranslation": {"ar": "\u0646. \u0628\u0627\u064a\u0631\u0627\u0645\u064a"}}}, "isHome": false, "shotType": "miss", "situation": "fast-break", "playerCoordinates": {"x": 15.1, "y": 67.3, "z": 0}, "bodyPart": "right-foot", "goalMouthLocation": "high-right", "goalMouthCoordinates": {"x": 0, "y": 41, "z": 84.7}, "xg": 0.053882379084826, "id": 3378913, "time": 67, "timeSeconds": 3967, "draw": {"start": {"x": 67.3, "y": 15.1}, "end": {"x": 59, "y": 0}, "goal": {"x": 59, "y": 15.3}}, "reversedPeriodTime": 24, "reversedPeriodTimeSeconds": 1433, "incidentType": "shot"}, {"player": {"name": "Kristjan Asllani", "firstName": "", "lastName": "", "slug": "kristjan-asllani", "shortName": "K. Asllani", "position": "M", "jerseyNumber": "21", "userCount": 2806, "id": 996820, "fieldTranslations": {"nameTranslation": {"ar": "\u0643\u0631\u064a\u0633\u062a\u062c\u0627\u0646 \u0623\u0633\u0644\u0627\u0646\u064a"}, "shortNameTranslation": {"ar": "\u0643. \u0623\u0633\u0644\u0627\u0646\u064a"}}}, "isHome": false, "shotType": "save", "situation": "assisted", "playerCoordinates": {"x": 21.2, "y": 37.6, "z": 0}, "bodyPart": "right-foot", "goalMouthLocation": "low-centre", "goalMouthCoordinates": {"x": 0, "y": 49.1, "z": 3.2}, "blockCoordinates": {"x": 1.2, "y": 47.5, "z": 0}, "xg": 0.027587916702032, "xgot": 0.0431, "id": 3378912, "time": 63, "timeSeconds": 3766, "draw": {"start": {"x": 37.6, "y": 21.2}, "block": {"x": 47.5, "y": 1.2}, "end": {"x": 50.9, "y": 0}, "goal": {"x": 50.9, "y": 96.8}}, "reversedPeriodTime": 28, "reversedPeriodTimeSeconds": 1634, "incidentType": "shot"}, {"player": {"name": "Ivan Peri\u0161i\u0107", "slug": "ivan-perisic", "shortName": "I. Peri\u0161i\u0107", "position": "M", "jerseyNumber": "4", "userCount": 17557, "id": 38710, "fieldTranslations": {"nameTranslation": {"ar": "\u0625\u064a\u0641\u0627\u0646 \u0628\u064a\u0631\u064a\u0633\u064a"}, "shortNameTranslation": {"ar": "\u0625. \u0628\u064a\u0631\u064a\u0633\u064a"}}}, "isHome": true, "shotType": "save", "situation": "assisted", "playerCoordinates": {"x": 23.5, "y": 35.4, "z": 0}, "bodyPart": "left-foot", "goalMouthLocation": "low-right", "goalMouthCoordinates": {"x": 0, "y": 45.5, "z": 13.3}, "blockCoordinates": {"x": 2.8, "y": 47.1, "z": 0}, "xg": 0.039817687124014, "xgot": 0.4148, "id": 3378911, "time": 61, "timeSeconds": 3617, "draw": {"start": {"x": 35.4, "y": 23.5}, "block": {"x": 47.1, "y": 2.8}, "end": {"x": 54.5, "y": 0}, "goal": {"x": 54.5, "y": 86.7}}, "reversedPeriodTime": 30, "reversedPeriodTimeSeconds": 1783, "incidentType": "shot"}, {"player": {"name": "Luka Modri\u0107", "slug": "luka-modric", "shortName": "L. Modri\u0107", "position": "M", "jerseyNumber": "10", "userCount": 185171, "id": 15466, "fieldTranslations": {"nameTranslation": {"ar": "\u0645\u0648\u062f\u0631\u064a\u062a\u0634, \u0644\u0648\u0643\u0627"}, "shortNameTranslation": {"ar": "\u0644. \u0645\u0648\u062f\u0631\u064a\u062a\u0634"}}}, "isHome": true, "shotType": "block", "situation": "regular", "playerCoordinates": {"x": 22.8, "y": 66.7, "z": 0}, "bodyPart": "right-foot", "goalMouthLocation": "low-centre", "goalMouthCoordinates": {"x": 0, "y": 50.6, "z": 19}, "blockCoordinates": {"x": 15, "y": 60.3, "z": 0}, "xg": 0.014732322655618, "id": 3378910, "time": 59, "timeSeconds": 3533, "draw": {"start": {"x": 66.7, "y": 22.8}, "block": {"x": 60.3, "y": 15}, "end": {"x": 49.4, "y": 0}, "goal": {"x": 49.4, "y": 81}}, "reversedPeriodTime": 32, "reversedPeriodTimeSeconds": 1867, "incidentType": "shot"}, {"player": {"name": "Josip \u0160utalo", "firstName": "", "lastName": "", "slug": "josip-sutalo", "shortName": "J. \u0160utalo", "position": "D", "jerseyNumber": "37", "userCount": 3718, "id": 954836, "fieldTranslations": {"nameTranslation": {"ar": "\u0633\u0648\u062a\u0627\u0644\u0648, \u062c\u0648\u0633\u064a\u0628"}, "shortNameTranslation": {"ar": "\u062c. \u0633\u0648\u062a\u0627\u0644\u0648"}}}, "isHome": true, "shotType": "miss", "situation": "corner", "playerCoordinates": {"x": 1.2, "y": 45.4, "z": 0}, "bodyPart": "head", "goalMouthLocation": "close-left", "goalMouthCoordinates": {"x": 0, "y": 58.2, "z": 31.9}, "xg": 0.60543191432953, "id": 3378891, "time": 58, "timeSeconds": 3434, "draw": {"start": {"x": 45.4, "y": 1.2}, "end": {"x": 41.8, "y": 0}, "goal": {"x": 41.8, "y": 68.1}}, "reversedPeriodTime": 33, "reversedPeriodTimeSeconds": 1966, "incidentType": "shot"}, {"player": {"name": "Bruno Petkovi\u0107", "firstName": "", "lastName": "", "slug": "bruno-petkovic", "shortName": "B. Petkovi\u0107", "position": "F", "jerseyNumber": "9", "userCount": 5626, "id": 309306, "fieldTranslations": {"nameTranslation": {"ar": "\u0628\u0631\u0648\u0646\u0648 \u067e\u064a\u062a\u0643\u0648\u06a2\u064a\u0643"}, "shortNameTranslation": {"ar": "\u0628. \u067e\u064a\u062a\u0643\u0648\u06a2\u064a\u0643"}}}, "isHome": true, "shotType": "block", "situation": "assisted", "playerCoordinates": {"x": 7.9, "y": 48.5, "z": 0}, "bodyPart": "head", "goalMouthLocation": "low-right", "goalMouthCoordinates": {"x": 0, "y": 47.1, "z": 19}, "blockCoordinates": {"x": 6.8, "y": 49.1, "z": 0}, "xg": 0.10002563893795, "id": 3378890, "time": 57, "timeSeconds": 3406, "draw": {"start": {"x": 48.5, "y": 7.9}, "block": {"x": 49.1, "y": 6.8}, "end": {"x": 52.9, "y": 0}, "goal": {"x": 52.9, "y": 81}}, "reversedPeriodTime": 34, "reversedPeriodTimeSeconds": 1994, "incidentType": "shot"}, {"player": {"name": "Mario Pa\u0161ali\u0107", "slug": "mario-pasalic", "shortName": "M. Pa\u0161ali\u0107", "position": "M", "jerseyNumber": "8", "userCount": 6916, "id": 190437, "fieldTranslations": {"nameTranslation": {"ar": "\u0628\u0627\u0632\u0627\u0644\u064a\u062a\u0634, \u0645\u0627\u0631\u064a\u0648"}, "shortNameTranslation": {"ar": "\u0645. \u0628\u0627\u0632\u0627\u0644\u064a\u062a\u0634"}}}, "isHome": true, "shotType": "miss", "situation": "assisted", "playerCoordinates": {"x": 7.9, "y": 57.9, "z": 0}, "bodyPart": "head", "goalMouthLocation": "right", "goalMouthCoordinates": {"x": 0, "y": 39.2, "z": 33.3}, "xg": 0.052451480180025, "id": 3378889, "time": 54, "timeSeconds": 3226, "draw": {"start": {"x": 57.9, "y": 7.9}, "end": {"x": 60.8, "y": 0}, "goal": {"x": 60.8, "y": 66.7}}, "reversedPeriodTime": 37, "reversedPeriodTimeSeconds": 2174, "incidentType": "shot"}, {"player": {"name": "Mateo Kova\u010di\u0107", "slug": "mateo-kovacic", "shortName": "M. Kova\u010di\u0107", "position": "M", "jerseyNumber": "8", "userCount": 26243, "id": 136710, "fieldTranslations": {"nameTranslation": {"ar": "\u0643\u0648\u0641\u0627\u0633\u064a\u062a\u0634, \u0645\u0627\u062a\u064a\u0648"}, "shortNameTranslation": {"ar": "\u0645. \u0643\u0648\u0641\u0627\u0633\u064a\u062a\u0634"}}}, "isHome": true, "shotType": "save", "situation": "assisted", "playerCoordinates": {"x": 22.5, "y": 40.5, "z": 0}, "bodyPart": "right-foot", "goalMouthLocation": "high-centre", "goalMouthCoordinates": {"x": 0, "y": 51.5, "z": 22.8}, "blockCoordinates": {"x": 3.7, "y": 47.8, "z": 0}, "xg": 0.037650853395462, "xgot": 0.0671, "id": 3378888, "time": 53, "timeSeconds": 3173, "draw": {"start": {"x": 40.5, "y": 22.5}, "block": {"x": 47.8, "y": 3.7}, "end": {"x": 48.5, "y": 0}, "goal": {"x": 48.5, "y": 77.2}}, "reversedPeriodTime": 38, "reversedPeriodTimeSeconds": 2227, "incidentType": "shot"}, {"player": {"name": "Mario Pa\u0161ali\u0107", "slug": "mario-pasalic", "shortName": "M. Pa\u0161ali\u0107", "position": "M", "jerseyNumber": "8", "userCount": 6916, "id": 190437, "fieldTranslations": {"nameTranslation": {"ar": "\u0628\u0627\u0632\u0627\u0644\u064a\u062a\u0634, \u0645\u0627\u0631\u064a\u0648"}, "shortNameTranslation": {"ar": "\u0645. \u0628\u0627\u0632\u0627\u0644\u064a\u062a\u0634"}}}, "isHome": true, "shotType": "miss", "situation": "assisted", "playerCoordinates": {"x": 4.6, "y": 56.1, "z": 0}, "bodyPart": "head", "goalMouthLocation": "high", "goalMouthCoordinates": {"x": 0, "y": 46.6, "z": 70.8}, "xg": 0.13861235976219, "id": 3378887, "time": 51, "timeSeconds": 3006, "draw": {"start": {"x": 56.1, "y": 4.6}, "end": {"x": 53.4, "y": 0}, "goal": {"x": 53.4, "y": 29.2}}, "reversedPeriodTime": 40, "reversedPeriodTimeSeconds": 2394, "incidentType": "shot"}, {"player": {"name": "Luka Su\u010di\u0107", "firstName": "", "lastName": "", "slug": "luka-sucic", "shortName": "L. Su\u010di\u0107", "position": "M", "jerseyNumber": "10", "userCount": 4131, "id": 949156, "fieldTranslations": {"nameTranslation": {"ar": "\u0644\u0648\u0643\u0627 \u0633\u0648\u062a\u0634\u064a\u062a\u0634"}, "shortNameTranslation": {"ar": "\u0644. \u0633\u0648\u062a\u0634\u064a\u062a\u0634"}}}, "isHome": true, "shotType": "save", "situation": "assisted", "playerCoordinates": {"x": 12.2, "y": 65.3, "z": 0}, "bodyPart": "left-foot", "goalMouthLocation": "low-centre", "goalMouthCoordinates": {"x": 0, "y": 51.8, "z": 5.1}, "blockCoordinates": {"x": 1.9, "y": 52.3, "z": 0}, "xg": 0.035219836980104, "xgot": 0.1123, "id": 3378886, "time": 50, "timeSeconds": 2982, "draw": {"start": {"x": 65.3, "y": 12.2}, "block": {"x": 52.3, "y": 1.9}, "end": {"x": 48.2, "y": 0}, "goal": {"x": 48.2, "y": 94.9}}, "reversedPeriodTime": 41, "reversedPeriodTimeSeconds": 2418, "incidentType": "shot"}, {"player": {"name": "Bruno Petkovi\u0107", "firstName": "", "lastName": "", "slug": "bruno-petkovic", "shortName": "B. Petkovi\u0107", "position": "F", "jerseyNumber": "9", "userCount": 5626, "id": 309306, "fieldTranslations": {"nameTranslation": {"ar": "\u0628\u0631\u0648\u0646\u0648 \u067e\u064a\u062a\u0643\u0648\u06a2\u064a\u0643"}, "shortNameTranslation": {"ar": "\u0628. \u067e\u064a\u062a\u0643\u0648\u06a2\u064a\u0643"}}}, "isHome": true, "shotType": "block", "situation": "assisted", "playerCoordinates": {"x": 8.5, "y": 44, "z": 0}, "bodyPart": "head", "goalMouthLocation": "low-centre", "goalMouthCoordinates": {"x": 0, "y": 49, "z": 19}, "blockCoordinates": {"x": 7.3, "y": 44.9, "z": 0}, "xg": 0.05502612516284, "id": 3378856, "time": 47, "timeSeconds": 2775, "draw": {"start": {"x": 44, "y": 8.5}, "block": {"x": 44.9, "y": 7.3}, "end": {"x": 51, "y": 0}, "goal": {"x": 51, "y": 81}}, "reversedPeriodTime": 44, "reversedPeriodTimeSeconds": 2625, "incidentType": "shot"}, {"player": {"name": "Rey Manaj", "firstName": "", "lastName": "", "slug": "rey-manaj", "shortName": "R. Manaj", "position": "F", "jerseyNumber": "9", "userCount": 1857, "id": 587882, "fieldTranslations": {"nameTranslation": {"ar": "\u0631\u0627\u064a \u0645\u0627\u0646\u0627\u064a"}, "shortNameTranslation": {"ar": "\u0631. \u0645\u0627\u0646\u0627\u064a"}}}, "isHome": false, "shotType": "save", "situation": "assisted", "playerCoordinates": {"x": 9.8, "y": 47, "z": 0}, "bodyPart": "head", "goalMouthLocation": "low-left", "goalMouthCoordinates": {"x": 0, "y": 53.1, "z": 17.1}, "blockCoordinates": {"x": 1.9, "y": 49.3, "z": 0}, "xg": 0.11438076943159, "xgot": 0.4751, "id": 3378855, "time": 45, "addedTime": 1, "timeSeconds": 2735, "draw": {"start": {"x": 47, "y": 9.8}, "block": {"x": 49.3, "y": 1.9}, "end": {"x": 46.9, "y": 0}, "goal": {"x": 46.9, "y": 82.9}}, "reversedPeriodTime": 1, "reversedPeriodTimeSeconds": 2665, "incidentType": "shot"}, {"player": {"name": "Jasir Asani", "slug": "jasir-asani", "shortName": "J. Asani", "position": "M", "jerseyNumber": "44", "userCount": 684, "id": 355022}, "isHome": false, "shotType": "block", "situation": "assisted", "playerCoordinates": {"x": 25.4, "y": 70.1, "z": 0}, "bodyPart": "left-foot", "goalMouthLocation": "low-centre", "goalMouthCoordinates": {"x": 0, "y": 48.6, "z": 19}, "blockCoordinates": {"x": 24.1, "y": 69.1, "z": 0}, "xg": 0.010986030101776, "id": 3378854, "time": 45, "addedTime": 1, "timeSeconds": 2730, "draw": {"start": {"x": 70.1, "y": 25.4}, "block": {"x": 69.1, "y": 24.1}, "end": {"x": 51.4, "y": 0}, "goal": {"x": 51.4, "y": 81}}, "reversedPeriodTime": 1, "reversedPeriodTimeSeconds": 2670, "incidentType": "shot"}, {"player": {"name": "Lovro Majer", "firstName": "", "lastName": "", "slug": "lovro-majer", "shortName": "L. Majer", "position": "M", "jerseyNumber": "19", "userCount": 5832, "id": 841947, "fieldTranslations": {"nameTranslation": {"ar": "\u0645\u0627\u062c\u0631, \u0644\u0648\u0641\u0631\u0648"}, "shortNameTranslation": {"ar": "\u0644. \u0645\u0627\u062c\u0631"}}}, "isHome": true, "shotType": "block", "situation": "assisted", "playerCoordinates": {"x": 10.2, "y": 54, "z": 0}, "bodyPart": "head", "goalMouthLocation": "low-left", "goalMouthCoordinates": {"x": 0, "y": 52.4, "z": 19}, "blockCoordinates": {"x": 9.3, "y": 53.4, "z": 0}, "xg": 0.05034189298749, "id": 3378853, "time": 43, "timeSeconds": 2537, "draw": {"start": {"x": 54, "y": 10.2}, "block": {"x": 53.4, "y": 9.3}, "end": {"x": 47.6, "y": 0}, "goal": {"x": 47.6, "y": 81}}, "reversedPeriodTime": 3, "reversedPeriodTimeSeconds": 163, "incidentType": "shot"}, {"player": {"name": "Marcelo Brozovi\u0107", "slug": "marcelo-brozovic", "shortName": "M. Brozovi\u0107", "position": "M", "jerseyNumber": "77", "userCount": 13981, "id": 108800, "fieldTranslations": {"nameTranslation": {"ar": "\u0645\u0627\u0631\u0633\u064a\u0644\u0648 \u0628\u0631\u0648\u0632\u0648\u0641\u064a\u062a\u0634"}, "shortNameTranslation": {"ar": "\u0645. \u0628\u0631\u0648\u0632\u0648\u0641\u064a\u062a\u0634"}}}, "isHome": true, "shotType": "save", "situation": "assisted", "playerCoordinates": {"x": 28.6, "y": 36.6, "z": 0}, "bodyPart": "right-foot", "goalMouthLocation": "low-centre", "goalMouthCoordinates": {"x": 0, "y": 51.3, "z": 8.9}, "blockCoordinates": {"x": 2.8, "y": 48.9, "z": 0}, "xg": 0.018535232171416, "xgot": 0.0322, "id": 3378915, "time": 38, "timeSeconds": 2274, "draw": {"start": {"x": 36.6, "y": 28.6}, "block": {"x": 48.9, "y": 2.8}, "end": {"x": 48.7, "y": 0}, "goal": {"x": 48.7, "y": 91.1}}, "reversedPeriodTime": 8, "reversedPeriodTimeSeconds": 426, "incidentType": "shot"}, {"player": {"name": "Kristjan Asllani", "firstName": "", "lastName": "", "slug": "kristjan-asllani", "shortName": "K. Asllani", "position": "M", "jerseyNumber": "21", "userCount": 2806, "id": 996820, "fieldTranslations": {"nameTranslation": {"ar": "\u0643\u0631\u064a\u0633\u062a\u062c\u0627\u0646 \u0623\u0633\u0644\u0627\u0646\u064a"}, "shortNameTranslation": {"ar": "\u0643. \u0623\u0633\u0644\u0627\u0646\u064a"}}}, "isHome": false, "shotType": "save", "situation": "fast-break", "playerCoordinates": {"x": 12.1, "y": 46.9, "z": 0}, "bodyPart": "right-foot", "goalMouthLocation": "low-left", "goalMouthCoordinates": {"x": 0, "y": 52.1, "z": 13.9}, "blockCoordinates": {"x": 5.4, "y": 48.6, "z": 0}, "xg": 0.14704237878323, "xgot": 0.5934, "id": 3378851, "time": 31, "timeSeconds": 1828, "draw": {"start": {"x": 46.9, "y": 12.1}, "block": {"x": 48.6, "y": 5.4}, "end": {"x": 47.9, "y": 0}, "goal": {"x": 47.9, "y": 86.1}}, "reversedPeriodTime": 15, "reversedPeriodTimeSeconds": 872, "incidentType": "shot"}, {"player": {"name": "Elseid Hysaj", "slug": "elseid-hysaj", "shortName": "E. Hysaj", "position": "D", "jerseyNumber": "23", "userCount": 1233, "id": 136322, "fieldTranslations": {"nameTranslation": {"ar": "\u0647\u064a\u0633\u0627\u062c \u0627\u0644\u0633\u0639\u064a\u062f"}, "shortNameTranslation": {"ar": "\u0647. \u0627\u0644\u0633\u0639\u064a\u062f"}}}, "isHome": false, "shotType": "miss", "situation": "regular", "playerCoordinates": {"x": 15.4, "y": 54.6, "z": 0}, "bodyPart": "left-foot", "goalMouthLocation": "high-left", "goalMouthCoordinates": {"x": 0, "y": 69.9, "z": 98.6}, "xg": 0.094113349914551, "id": 3378850, "time": 29, "timeSeconds": 1726, "draw": {"start": {"x": 54.6, "y": 15.4}, "end": {"x": 30.1, "y": 0}, "goal": {"x": 30.1, "y": 1.4}}, "reversedPeriodTime": 17, "reversedPeriodTimeSeconds": 974, "incidentType": "shot"}, {"player": {"name": "Rey Manaj", "firstName": "", "lastName": "", "slug": "rey-manaj", "shortName": "R. Manaj", "position": "F", "jerseyNumber": "9", "userCount": 1857, "id": 587882, "fieldTranslations": {"nameTranslation": {"ar": "\u0631\u0627\u064a \u0645\u0627\u0646\u0627\u064a"}, "shortNameTranslation": {"ar": "\u0631. \u0645\u0627\u0646\u0627\u064a"}}}, "isHome": false, "shotType": "block", "situation": "assisted", "playerCoordinates": {"x": 9.4, "y": 56.5, "z": 0}, "bodyPart": "head", "goalMouthLocation": "low-centre", "goalMouthCoordinates": {"x": 0, "y": 51.6, "z": 19}, "blockCoordinates": {"x": 8.8, "y": 56, "z": 0}, "xg": 0.035533055663109, "id": 3378852, "time": 29, "timeSeconds": 1724, "draw": {"start": {"x": 56.5, "y": 9.4}, "block": {"x": 56, "y": 8.8}, "end": {"x": 48.4, "y": 0}, "goal": {"x": 48.4, "y": 81}}, "reversedPeriodTime": 17, "reversedPeriodTimeSeconds": 976, "incidentType": "shot"}, {"player": {"name": "Bruno Petkovi\u0107", "firstName": "", "lastName": "", "slug": "bruno-petkovic", "shortName": "B. Petkovi\u0107", "position": "F", "jerseyNumber": "9", "userCount": 5626, "id": 309306, "fieldTranslations": {"nameTranslation": {"ar": "\u0628\u0631\u0648\u0646\u0648 \u067e\u064a\u062a\u0643\u0648\u06a2\u064a\u0643"}, "shortNameTranslation": {"ar": "\u0628. \u067e\u064a\u062a\u0643\u0648\u06a2\u064a\u0643"}}}, "isHome": true, "shotType": "miss", "situation": "assisted", "playerCoordinates": {"x": 9.2, "y": 49.9, "z": 0}, "bodyPart": "head", "goalMouthLocation": "high-right", "goalMouthCoordinates": {"x": 0, "y": 40.7, "z": 69.4}, "xg": 0.13385365903378, "id": 3378849, "time": 26, "timeSeconds": 1556, "draw": {"start": {"x": 49.9, "y": 9.2}, "end": {"x": 59.3, "y": 0}, "goal": {"x": 59.3, "y": 30.6}}, "reversedPeriodTime": 20, "reversedPeriodTimeSeconds": 1144, "incidentType": "shot"}, {"player": {"name": "Marcelo Brozovi\u0107", "slug": "marcelo-brozovic", "shortName": "M. Brozovi\u0107", "position": "M", "jerseyNumber": "77", "userCount": 13981, "id": 108800, "fieldTranslations": {"nameTranslation": {"ar": "\u0645\u0627\u0631\u0633\u064a\u0644\u0648 \u0628\u0631\u0648\u0632\u0648\u0641\u064a\u062a\u0634"}, "shortNameTranslation": {"ar": "\u0645. \u0628\u0631\u0648\u0632\u0648\u0641\u064a\u062a\u0634"}}}, "isHome": true, "shotType": "miss", "situation": "assisted", "playerCoordinates": {"x": 17.8, "y": 68.7, "z": 0}, "bodyPart": "right-foot", "goalMouthLocation": "left", "goalMouthCoordinates": {"x": 0, "y": 60.7, "z": 6.9}, "xg": 0.033834978938103, "id": 3378847, "time": 20, "timeSeconds": 1184, "draw": {"start": {"x": 68.7, "y": 17.8}, "end": {"x": 39.3, "y": 0}, "goal": {"x": 39.3, "y": 93.1}}, "reversedPeriodTime": 26, "reversedPeriodTimeSeconds": 1516, "incidentType": "shot"}, {"player": {"name": "Mateo Kova\u010di\u0107", "slug": "mateo-kovacic", "shortName": "M. Kova\u010di\u0107", "position": "M", "jerseyNumber": "8", "userCount": 26243, "id": 136710, "fieldTranslations": {"nameTranslation": {"ar": "\u0643\u0648\u0641\u0627\u0633\u064a\u062a\u0634, \u0645\u0627\u062a\u064a\u0648"}, "shortNameTranslation": {"ar": "\u0645. \u0643\u0648\u0641\u0627\u0633\u064a\u062a\u0634"}}}, "isHome": true, "shotType": "block", "situation": "assisted", "playerCoordinates": {"x": 25, "y": 38.9, "z": 0}, "bodyPart": "right-foot", "goalMouthLocation": "low-centre", "goalMouthCoordinates": {"x": 0, "y": 49.3, "z": 19}, "blockCoordinates": {"x": 21.4, "y": 40.6, "z": 0}, "xg": 0.024019191041589, "id": 3378848, "time": 20, "timeSeconds": 1174, "draw": {"start": {"x": 38.9, "y": 25}, "block": {"x": 40.6, "y": 21.4}, "end": {"x": 50.7, "y": 0}, "goal": {"x": 50.7, "y": 81}}, "reversedPeriodTime": 26, "reversedPeriodTimeSeconds": 1526, "incidentType": "shot"}, {"player": {"name": "Elseid Hysaj", "slug": "elseid-hysaj", "shortName": "E. Hysaj", "position": "D", "jerseyNumber": "23", "userCount": 1233, "id": 136322, "fieldTranslations": {"nameTranslation": {"ar": "\u0647\u064a\u0633\u0627\u062c \u0627\u0644\u0633\u0639\u064a\u062f"}, "shortNameTranslation": {"ar": "\u0647. \u0627\u0644\u0633\u0639\u064a\u062f"}}}, "isHome": false, "shotType": "block", "situation": "corner", "playerCoordinates": {"x": 21.6, "y": 57.7, "z": 0}, "bodyPart": "left-foot", "goalMouthLocation": "low-left", "goalMouthCoordinates": {"x": 0, "y": 52.3, "z": 19}, "blockCoordinates": {"x": 15.9, "y": 55.1, "z": 0}, "xg": 0.026372397318482, "id": 3378846, "time": 16, "timeSeconds": 907, "draw": {"start": {"x": 57.7, "y": 21.6}, "block": {"x": 55.1, "y": 15.9}, "end": {"x": 47.7, "y": 0}, "goal": {"x": 47.7, "y": 81}}, "reversedPeriodTime": 30, "reversedPeriodTimeSeconds": 1793, "incidentType": "shot"}, {"player": {"name": "Nedim Bajrami", "firstName": "", "lastName": "", "slug": "nedim-bajrami", "shortName": "N. Bajrami", "position": "M", "jerseyNumber": "11", "userCount": 1625, "id": 825861, "fieldTranslations": {"nameTranslation": {"ar": "\u0646\u062f\u064a\u0645 \u0628\u0627\u064a\u0631\u0627\u0645\u064a"}, "shortNameTranslation": {"ar": "\u0646. \u0628\u0627\u064a\u0631\u0627\u0645\u064a"}}}, "isHome": false, "shotType": "block", "situation": "assisted", "playerCoordinates": {"x": 11.4, "y": 28.3, "z": 0}, "bodyPart": "right-foot", "goalMouthLocation": "low-left", "goalMouthCoordinates": {"x": 0, "y": 53.7, "z": 19}, "blockCoordinates": {"x": 10.5, "y": 29.8, "z": 0}, "xg": 0.020764825865626, "id": 3378845, "time": 15, "timeSeconds": 866, "draw": {"start": {"x": 28.3, "y": 11.4}, "block": {"x": 29.8, "y": 10.5}, "end": {"x": 46.3, "y": 0}, "goal": {"x": 46.3, "y": 81}}, "reversedPeriodTime": 31, "reversedPeriodTimeSeconds": 1834, "incidentType": "shot"}, {"player": {"name": "Qazim Laci", "firstName": "", "lastName": "", "slug": "qazim-laci", "shortName": "Q. Laci", "position": "M", "jerseyNumber": "20", "userCount": 468, "id": 284395, "fieldTranslations": {"nameTranslation": {"ar": "\u0643\u0627\u0632\u064a\u0645 \u0644\u0627\u0633\u064a"}, "shortNameTranslation": {"ar": "\u0643. \u0644\u0627\u0633\u064a"}}}, "isHome": false, "shotType": "goal", "goalType": "regular", "situation": "assisted", "playerCoordinates": {"x": 6.9, "y": 54.5, "z": 0}, "bodyPart": "head", "goalMouthLocation": "low-right", "goalMouthCoordinates": {"x": 0, "y": 47.7, "z": 5.1}, "xg": 0.33544310927391, "xgot": 0.4744, "id": 3378844, "time": 11, "timeSeconds": 615, "draw": {"start": {"x": 54.5, "y": 6.9}, "end": {"x": 52.3, "y": 0}, "goal": {"x": 52.3, "y": 94.9}}, "reversedPeriodTime": 35, "reversedPeriodTimeSeconds": 2085, "incidentType": "shot"}]